snow_way_out/ServiceNowAPI.py
snow_way_out/__init__.py
snow_way_out-0.0.2.dist-info/LICENSE
snow_way_out-0.0.2.dist-info/METADATA
snow_way_out-0.0.2.dist-info/WHEEL
snow_way_out-0.0.2.dist-info/top_level.txt
snow_way_out-0.0.2.dist-info/RECORD
