Metadata-Version: 2.1
Name: snow-way-out
Version: 0.0.2
Author-email: Brian Lee <brian.baligad.lee@zayo.com>
License: Apache License
Project-URL: Homepage, https://github.com/bleetube/snow-way-out
Classifier: Programming Language :: Python
Classifier: Programming Language :: Python :: 3
Classifier: Programming Language :: Python :: 3.11
Classifier: Programming Language :: Python :: 3.12
Classifier: Programming Language :: Python :: Implementation :: CPython
Classifier: Programming Language :: Python :: Implementation :: PyPy
Classifier: Topic :: System :: Monitoring
Requires-Python: >=3.11.6
License-File: LICENSE
Requires-Dist: build >=1.0.0
Requires-Dist: requests >=2.0.0
Requires-Dist: pytest >=8.0.0
